rr_connection_manager/__init__.py
rr_connection_manager/classes/__init__.py
rr_connection_manager/classes/connection.py
rr_connection_manager/classes/connection_conf.py
rr_connection_manager/classes/mysql_connection.py
rr_connection_manager/classes/postgres_connection.py
rr_connection_manager/classes/redis_connection.py
rr_connection_manager/classes/sql_server_connection.py
rr_connection_manager/classes/sqlite_connection.py
rr_connection_manager-0.5.2.dist-info/LICENSE
rr_connection_manager-0.5.2.dist-info/METADATA
rr_connection_manager-0.5.2.dist-info/WHEEL
rr_connection_manager-0.5.2.dist-info/RECORD
