Metadata-Version: 2.3
Name: rr-connection-manager
Version: 0.5.2
Summary: A package to help you connect to all Registry databases
License: MIT
Author: andrew atterton
Author-email: andrew.atterton@renalregistry.nhs.uk
Requires-Python: >=3.8,<4.0
Classifier: License :: OSI Approved :: MIT License
Classifier: Programming Language :: Python :: 3
Classifier: Programming Language :: Python :: 3.8
Classifier: Programming Language :: Python :: 3.9
Classifier: Programming Language :: Python :: 3.10
Classifier: Programming Language :: Python :: 3.11
Classifier: Programming Language :: Python :: 3.12
Classifier: Programming Language :: Python :: 3.13
Provides-Extra: keepass
Provides-Extra: mysql
Provides-Extra: mysql-sqla
Provides-Extra: pgsql
Provides-Extra: pgsql-sqla
Provides-Extra: redis
Provides-Extra: sqlite-sqla
Provides-Extra: sqlser
Provides-Extra: sqlser-sqla
Provides-Extra: tunnel
Requires-Dist: mysql-connector-python (==8.1.0) ; extra == "mysql" or extra == "mysql-sqla"
Requires-Dist: psycopg (>=3.2.3,<4.0.0) ; extra == "pgsql" or extra == "pgsql-sqla"
Requires-Dist: pykeepass (>=4.1.0.post1,<5.0.0) ; extra == "keepass"
Requires-Dist: pyodbc (>=5.2.0,<6.0.0) ; extra == "sqlser" or extra == "sqlser-sqla"
Requires-Dist: redis (>=5.2.0,<6.0.0) ; extra == "redis"
Requires-Dist: sqlalchemy (>=2.0.36,<3.0.0) ; extra == "sqlite-sqla" or extra == "pgsql-sqla" or extra == "sqlser-sqla" or extra == "mysql-sqla"
Requires-Dist: sshtunnel (>=0.4.0,<0.5.0) ; extra == "tunnel"
